mkdocs_jupyter/__about__.py
mkdocs_jupyter/__init__.py
mkdocs_jupyter/config.py
mkdocs_jupyter/convert.py
mkdocs_jupyter/nbconvert2.py
mkdocs_jupyter/plugin.py
mkdocs_jupyter/preprocessors.py
mkdocs_jupyter/utils.py
mkdocs_jupyter/templates/mkdocs_html/conf.json
mkdocs_jupyter/templates/mkdocs_html/notebook.html.j2
mkdocs_jupyter/templates/mkdocs_html/assets/.gitignore
mkdocs_jupyter/templates/mkdocs_html/assets/clipboard.umd.js
mkdocs_jupyter/templates/mkdocs_html/assets/dark.js
mkdocs_jupyter/templates/mkdocs_html/assets/index.css
mkdocs_jupyter/templates/mkdocs_html/assets/index.js
mkdocs_jupyter/templates/mkdocs_html/assets/light.js
mkdocs_jupyter/templates/mkdocs_html/assets/theme-dark.css
mkdocs_jupyter/templates/mkdocs_html/assets/theme-light.css
mkdocs_jupyter/templates/mkdocs_md/conf.json
mkdocs_jupyter/templates/mkdocs_md/md-no-codecell.md.j2
mkdocs_jupyter/tests/__init__.py
mkdocs_jupyter/tests/test_base_usage.py
mkdocs_jupyter/tests/test_pkg.py
mkdocs_jupyter/tests/test_toc.py
mkdocs_jupyter/tests/mkdocs/base-with-nbs-failure.yml
mkdocs_jupyter/tests/mkdocs/base-with-nbs-pys.yml
mkdocs_jupyter/tests/mkdocs/base-with-nbs.yml
mkdocs_jupyter/tests/mkdocs/base-with-pys.yml
mkdocs_jupyter/tests/mkdocs/base-without-nbs.yml
mkdocs_jupyter/tests/mkdocs/material-execute-ignore.yml
mkdocs_jupyter/tests/mkdocs/material-with-nbs-pys.yml
mkdocs_jupyter/tests/mkdocs/material-with-nbs.yml
mkdocs_jupyter/tests/mkdocs/material-with-pys.yml
mkdocs_jupyter/tests/mkdocs/docs/backquote_toc_test.ipynb
mkdocs_jupyter/tests/mkdocs/docs/demo-script.py
mkdocs_jupyter/tests/mkdocs/docs/demo.ipynb
mkdocs_jupyter/tests/mkdocs/docs/fail.ipynb
mkdocs_jupyter/tests/mkdocs/docs/index.md
mkdocs_jupyter/tests/mkdocs/docs/ruby.ipynb
mkdocs_jupyter/tests/mkdocs/docs/variational-inference-script.py
mkdocs_jupyter/tests/mkdocs/docs/variational-inference.ipynb
mkdocs_jupyter/tests/mkdocs/docs/extras/README.md
mkdocs_jupyter/tests/mkdocs/docs/extras/default.css
mkdocs_jupyter-0.24.8.dist-info/METADATA
mkdocs_jupyter-0.24.8.dist-info/WHEEL
mkdocs_jupyter-0.24.8.dist-info/entry_points.txt
mkdocs_jupyter-0.24.8.dist-info/licenses/LICENSE.txt
mkdocs_jupyter-0.24.8.dist-info/RECORD
