Metadata-Version: 2.3
Name: mkdocs-jupyter
Version: 0.24.8
Summary: Use Jupyter in mkdocs websites
Project-URL: Documentation, https://github.com/danielfrg/mkdocs-jupyter#readme
Project-URL: Issues, https://github.com/danielfrg/mkdocs-jupyter/issues
Project-URL: Source, https://github.com/danielfrg/mkdocs-jupyter
Author-email: Daniel Rodriguez <daniel@danielfrg.com>
License: Apache-2.0
License-File: LICENSE.txt
Keywords: documentation,jupyter,jupyterlab,mkdocs,notebooks
Classifier: Development Status :: 5 - Production/Stable
Classifier: Programming Language :: Python
Classifier: Programming Language :: Python :: 3.8
Classifier: Programming Language :: Python :: 3.9
Classifier: Programming Language :: Python :: 3.10
Classifier: Programming Language :: Python :: 3.11
Classifier: Programming Language :: Python :: Implementation :: CPython
Classifier: Programming Language :: Python :: Implementation :: PyPy
Requires-Python: >=3.8
Requires-Dist: ipykernel<7.0.0,>6.0.0
Requires-Dist: jupytext<2,>1.13.8
Requires-Dist: mkdocs-material>9.0.0
Requires-Dist: mkdocs<2,>=1.4.0
Requires-Dist: nbconvert<8,>=7.2.9
Requires-Dist: pygments>2.12.0
